fastapi_loopguard/__init__.py
fastapi_loopguard/config.py
fastapi_loopguard/context.py
fastapi_loopguard/logging.py
fastapi_loopguard/metrics.py
fastapi_loopguard/middleware.py
fastapi_loopguard/monitor.py
fastapi_loopguard/py.typed
fastapi_loopguard/pytest_plugin.py
fastapi_loopguard-0.4.1.dist-info/METADATA
fastapi_loopguard-0.4.1.dist-info/WHEEL
fastapi_loopguard-0.4.1.dist-info/entry_points.txt
fastapi_loopguard-0.4.1.dist-info/licenses/LICENSE
fastapi_loopguard-0.4.1.dist-info/RECORD
