Metadata-Version: 2.4
Name: fastapi-loopguard
Version: 0.4.1
Summary: Detect event-loop blocking in FastAPI/Starlette with per-request attribution
Project-URL: Homepage, https://github.com/parhamdavari/fastapi-loopguard
Project-URL: Documentation, https://github.com/parhamdavari/fastapi-loopguard#readme
Project-URL: Repository, https://github.com/parhamdavari/fastapi-loopguard
Project-URL: Issues, https://github.com/parhamdavari/fastapi-loopguard/issues
Author: Parham
License-Expression: MIT
License-File: LICENSE
Keywords: asyncio,blocking,event-loop,fastapi,middleware,monitoring,performance,starlette
Classifier: Development Status :: 4 - Beta
Classifier: Framework :: AsyncIO
Classifier: Framework :: FastAPI
Classifier: Intended Audience :: Developers
Classifier: License :: OSI Approved :: MIT License
Classifier: Programming Language :: Python :: 3
Classifier: Programming Language :: Python :: 3.12
Classifier: Programming Language :: Python :: 3.13
Classifier: Topic :: Software Development :: Libraries :: Python Modules
Classifier: Topic :: System :: Monitoring
Classifier: Typing :: Typed
Requires-Python: >=3.12
Requires-Dist: starlette<1.0,>=0.37.0
Provides-Extra: all
Requires-Dist: prometheus-client>=0.19.0; extra == 'all'
Requires-Dist: structlog>=24.1.0; extra == 'all'
Provides-Extra: dev
Requires-Dist: coverage>=7.4.0; extra == 'dev'
Requires-Dist: fastapi>=0.110.0; extra == 'dev'
Requires-Dist: httpx>=0.27.0; extra == 'dev'
Requires-Dist: mypy>=1.8.0; extra == 'dev'
Requires-Dist: pytest-asyncio>=0.23.0; extra == 'dev'
Requires-Dist: pytest>=8.0.0; extra == 'dev'
Requires-Dist: ruff>=0.3.0; extra == 'dev'
Provides-Extra: prometheus
Requires-Dist: prometheus-client>=0.19.0; extra == 'prometheus'
Provides-Extra: stress
Requires-Dist: locust>=2.20.0; extra == 'stress'
Requires-Dist: uvicorn>=0.27.0; extra == 'stress'
Provides-Extra: structlog
Requires-Dist: structlog>=24.1.0; extra == 'structlog'
